infinidata-0.0.1.dist-info/METADATA
infinidata-0.0.1.dist-info/WHEEL
infinidata/__init__.py
infinidata/infinidata.cpython-311-x86_64-linux-gnu.so
infinidata-0.0.1.dist-info/RECORD
