Metadata-Version: 2.1
Name: infinidata
Version: 0.0.1
Classifier: Programming Language :: Rust
Classifier: Programming Language :: Python :: Implementation :: CPython
Classifier: Programming Language :: Python :: Implementation :: PyPy
Summary: A Python library for transparently working with datasets much larger than memory.
Home-Page: https://github.com/enolan/infinidata
License: BSD-3-Clause
Requires-Python: >=3.8
